MANIFEST.in
README.md
publish
setup.py
modules/__init__.py
modules/channel.py
modules/consumer.py
modules/engine.py
modules/exception.py
modules/ui.py
plugins/__init__.py
plugins/blog.py
plugins/fb.py
plugins/mail.py
plugins/twitter.py
python_publish.egg-info/PKG-INFO
python_publish.egg-info/SOURCES.txt
python_publish.egg-info/dependency_links.txt
python_publish.egg-info/requires.txt
python_publish.egg-info/top_level.txt