Metadata-Version: 1.0
Name: python-publish
Version: 1.0.0
Summary: Program to broadcast an announcement on multiple social media channels
Home-page: https://github.com/alfie-max/publish
Author: Alfred Dominic, Shahul Hameed
Author-email: alfie.2012@gmail.com
License: UNKNOWN
Platform: UNKNOWN
